automation_error_detector/__init__.py
automation_error_detector/application/dto/error_result_dto.py
automation_error_detector/application/dto/screen_result_dto.py
automation_error_detector/application/use_cases/detect_error_use_case.py
automation_error_detector/application/use_cases/detect_screen_use_case.py
automation_error_detector/application/use_cases/phrase_learning_mixin.py
automation_error_detector/config/__init__.py
automation_error_detector/config/app_config.py
automation_error_detector/config/base.py
automation_error_detector/domain/__init__.py
automation_error_detector/domain/entities/error_signature.py
automation_error_detector/domain/services/ai_service.py
automation_error_detector/domain/services/cache_callback.py
automation_error_detector/domain/services/phrase_cache_service.py
automation_error_detector/domain/services/signature_service.py
automation_error_detector/domain/value_objects/keywords.py
automation_error_detector/domain/value_objects/screen_text.py
automation_error_detector/infrastructure/ai/openai_client.py
automation_error_detector/infrastructure/cache/cache_repository.py
automation_error_detector/infrastructure/cache/json_cache_repository.py
automation_error_detector/infrastructure/cache/json_phrase_cache.py
automation_error_detector/infrastructure/cache/redis_cache_repository.py
automation_error_detector/infrastructure/cache/redis_phrase_cache.py
automation_error_detector/shared/normalization.py
automation_error_detector/shared/text_dispatcher.py
automation_error_detector/shared/vi_text_processor.py
automation_error_detector-1.3.6.dist-info/METADATA
automation_error_detector-1.3.6.dist-info/WHEEL
automation_error_detector-1.3.6.dist-info/top_level.txt
automation_error_detector-1.3.6.dist-info/RECORD
