Metadata-Version: 2.4
Name: automation-error-detector
Version: 1.3.6
Summary: Automation browser error detection and screen detection with AI fallback and cache
Author: Kyle
Requires-Python: >=3.9
Requires-Dist: openai>=1.0.0
Requires-Dist: httpx[socks]
